{"nodes": [{"id": "site_api_reference_surface", "label": "API Reference Surface", "file_type": "document", "source_file": "docs/site/api.md", "source_location": "lines 1-75", "source_url": null, "captured_at": null, "author": null, "contributor": null}], "edges": [{"source": "site_api_reference_surface", "target": "site_gene_space_genespace", "relation": "references", "confidence": "EXTRACTED", "confidence_score": 1.0, "source_file": "docs/site/api.md", "source_location": "lines 1-12", "weight": 1.0}, {"source": "site_api_reference_surface", "target": "site_gene_space_repair_codec_helpers", "relation": "references", "confidence": "EXTRACTED", "confidence_score": 1.0, "source_file": "docs/site/api.md", "source_location": "lines 5-12", "weight": 1.0}, {"source": "site_api_reference_surface", "target": "site_de_differentialevolutionoptimizer", "relation": "references", "confidence": "EXTRACTED", "confidence_score": 1.0, "source_file": "docs/site/api.md", "source_location": "line 20", "weight": 1.0}, {"source": "site_api_reference_surface", "target": "site_ask_tell_engines_optimizer_protocol", "relation": "references", "confidence": "EXTRACTED", "confidence_score": 1.0, "source_file": "docs/site/api.md", "source_location": "lines 26-48", "weight": 1.0}, {"source": "site_api_reference_surface", "target": "site_budget_aware_optimization_budgetpolicy", "relation": "references", "confidence": "EXTRACTED", "confidence_score": 1.0, "source_file": "docs/site/api.md", "source_location": "lines 60-62", "weight": 1.0}], "hyperedges": []}